pydust/__init__.py
pydust/__main__.py
pydust/build.py
pydust/buildzig.py
pydust/config.py
pydust/generate_stubs.py
pydust/py.typed
pydust/pytest_plugin.py
pydust/src/attributes.zig
pydust/src/builtins.zig
pydust/src/conversions.zig
pydust/src/discovery.zig
pydust/src/errors.zig
pydust/src/ffi.h
pydust/src/functions.zig
pydust/src/mem.zig
pydust/src/modules.zig
pydust/src/pydust.build.zig
pydust/src/pydust.zig
pydust/src/pytypes.zig
pydust/src/trampoline.zig
pydust/src/types/bool.zig
pydust/src/types/buffer.zig
pydust/src/types/bytes.zig
pydust/src/types/code.zig
pydust/src/types/dict.zig
pydust/src/types/error.zig
pydust/src/types/float.zig
pydust/src/types/frame.zig
pydust/src/types/gil.zig
pydust/src/types/iter.zig
pydust/src/types/list.zig
pydust/src/types/long.zig
pydust/src/types/memoryview.zig
pydust/src/types/module.zig
pydust/src/types/obj.zig
pydust/src/types/slice.zig
pydust/src/types/str.zig
pydust/src/types/tuple.zig
pydust/src/types/type.zig
pydust/src/types.zig
ziggy_pydust-0.26.0.dist-info/LICENSE
ziggy_pydust-0.26.0.dist-info/METADATA
ziggy_pydust-0.26.0.dist-info/WHEEL
ziggy_pydust-0.26.0.dist-info/entry_points.txt
ziggy_pydust-0.26.0.dist-info/RECORD
