Metadata-Version: 2.1
Name: ziggy-pydust
Version: 0.26.0
Summary: 
License: Apache 2.0
Author: Nicholas Gates
Author-email: nick@fulcrum.so
Requires-Python: >=3.11,<4.0
Classifier: License :: Other/Proprietary License
Classifier: Programming Language :: Python :: 3
Classifier: Programming Language :: Python :: 3.11
Requires-Dist: black (>=25.0.0,<26.0.0)
Requires-Dist: pydantic (>=2.3.0,<3.0.0)
Requires-Dist: setuptools (>=80.0.0,<81.0.0)
Requires-Dist: ziglang (>=0.15.1,<0.16.0)
